qua_dashboards/__init__.py
qua_dashboards/app.py
qua_dashboards/cli.py
qua_dashboards/logging_config.py
qua_dashboards/assets/custom_clientside.js
qua_dashboards/assets/index.css
qua_dashboards/core/__init__.py
qua_dashboards/core/base_component.py
qua_dashboards/core/base_updatable_component.py
qua_dashboards/core/dashboard_builder.py
qua_dashboards/core/parameter_protocol.py
qua_dashboards/data_dashboard/__init__.py
qua_dashboards/data_dashboard/data_dashboard_app.py
qua_dashboards/data_dashboard/data_dashboard_client.py
qua_dashboards/data_dashboard/plotting.py
qua_dashboards/data_dashboard/data_components/__init__.py
qua_dashboards/data_dashboard/data_components/base_data_component.py
qua_dashboards/data_dashboard/data_components/data_array_component.py
qua_dashboards/data_dashboard/data_components/dataset_component.py
qua_dashboards/data_dashboard/data_components/image_component.py
qua_dashboards/data_dashboard/data_components/standard_component.py
qua_dashboards/data_dashboard/tests/debug_test.py
qua_dashboards/data_dashboard/tests/minimal_example_children_dict.py
qua_dashboards/data_dashboard/tests/update_graph_children.py
qua_dashboards/data_dashboard/tests/xarray_dataset_examples.py
qua_dashboards/data_dashboard/xarray_visualizer/data_generation.py
qua_dashboards/data_dashboard/xarray_visualizer/xarray_plotly.py
qua_dashboards/pages/__init__.py
qua_dashboards/pages/data_dashboard.py
qua_dashboards/pages/home.py
qua_dashboards/utils/__init__.py
qua_dashboards/utils/basic_parameter.py
qua_dashboards/utils/dash_utils.py
qua_dashboards/utils/data_utils.py
qua_dashboards/utils/general_utils.py
qua_dashboards/utils/log_utils.py
qua_dashboards/utils/qua_types.py
qua_dashboards/video_mode/README.md
qua_dashboards/video_mode/__init__.py
qua_dashboards/video_mode/data_registry.py
qua_dashboards/video_mode/shared_viewer_component.py
qua_dashboards/video_mode/sweep_axis.py
qua_dashboards/video_mode/video_mode_component.py
qua_dashboards/video_mode/voltage_parameter.py
qua_dashboards-0.2.0.dist-info/METADATA
qua_dashboards-0.2.0.dist-info/WHEEL
qua_dashboards-0.2.0.dist-info/entry_points.txt
qua_dashboards-0.2.0.dist-info/licenses/LICENSE
qua_dashboards-0.2.0.dist-info/RECORD
