Metadata-Version: 2.4
Name: qua-dashboards
Version: 0.2.0
Summary: Collection of dashboards for the QUA platform
Project-URL: Homepage, https://github.com/qua-platform/qua-dashboards/
Author-email: Quantum Machines <info@quantum-machines.co>
License-File: LICENSE
Requires-Python: <3.13,>=3.9
Requires-Dist: dash-bootstrap-components>=1.6.0
Requires-Dist: dash-dynamic-grid-layout>=0.1.3
Requires-Dist: dash-extensions>=1.0.19
Requires-Dist: dash>=2.18.2
Requires-Dist: ipykernel>=6.29.5
Requires-Dist: matplotlib>=3.9.0
Requires-Dist: pandas>=2.2.3
Requires-Dist: qualang-tools>=0.18.2
Requires-Dist: qualibrate-core>=0.3.1
Requires-Dist: xarray==2024.07.0
